parseur_retro_doc/__init__.py
parseur_retro_doc/bloc.py
parseur_retro_doc/client.py
parseur_retro_doc/code.py
parseur_retro_doc/commentaire.py
parseur_retro_doc/const_regex.py
parseur_retro_doc/parser.py
parseur_retro_doc/requete.py
parseur_retro_doc/script.py
parseur_retro_doc/table.py
parseur_retro_doc/variable.py
parser_retro_doc-0.0.1.dist-info/LICENSE
parser_retro_doc-0.0.1.dist-info/METADATA
parser_retro_doc-0.0.1.dist-info/WHEEL
parser_retro_doc-0.0.1.dist-info/top_level.txt
parser_retro_doc-0.0.1.dist-info/RECORD
