Metadata-Version: 2.1
Name: parser-retro-doc
Version: 0.0.1
Summary: A python module to parse source code for retro-documentation
Home-page: https://github.com/pypa/sampleproject
Author: Nicolas Bouillette, Guillaume Hurvois, Julien Mendes, Adam Wang
Author-email: nbouillette@bi-consulting.com, ghurvois@bi-consulting.com, jmendes@bi-consulting.com, awang@bi-consulting.com
License: UNKNOWN
Platform: UNKNOWN
Classifier: Development Status :: 3 - Alpha
Classifier: Intended Audience :: Developers
Classifier: Topic :: Software Development :: Build Tools
Classifier: Programming Language :: Python :: 3.7
Classifier: Programming Language :: Python :: 3.8
Classifier: Programming Language :: Python :: 3 :: Only
Requires-Python: >=3.5, <4
